{"data":{"allMarkdownRemark":{"edges":[{"node":{"fields":{"slug":"/til0140/"},"frontmatter":{"title":"Pytest Parametrize."}}},{"node":{"fields":{"slug":"/til0139/"},"frontmatter":{"title":"Python Hygiene."}}},{"node":{"fields":{"slug":"/til0138/"},"frontmatter":{"title":"GitLab Lint CI."}}},{"node":{"fields":{"slug":"/til0137/"},"frontmatter":{"title":"Postman Cheat Sheet."}}},{"node":{"fields":{"slug":"/til0136/"},"frontmatter":{"title":"SQL Cheat Sheet."}}},{"node":{"fields":{"slug":"/til0135/"},"frontmatter":{"title":"Python Basics: Cheat Sheet."}}}]}},"pageContext":{"limit":6,"skip":6,"numPages":34,"currentPage":2}}