{"data":{"markdownRemark":{"html":"<p>Here is some quick and easy Cypress to get you going:</p>\n<pre><code>cy.get(\"input\")\n.type(\"my text goes here\")\n.should(\"have.value\", \"my text goes here\");\n</code></pre>\n<pre><code>cy.get(\"input\")\n.invoke(\"attr\", \"placholder\")\n.should(\"contain\", \"Search\");\n</code></pre>\n<pre><code>cy.get(\"a\")\n.first()\n.click()\n.url()\n.should(\"include\", \"/yoururl\");\n</code></pre>\n<p><code>cy.get(\"h1\").contains(\"My heading\");</code></p>\n<p><code>cy.get(\"div.your-special-classname\").contains(\"Your spectial text...\");</code></p>\n<pre><code>cy.get(\"select\")\n.eq(1)\n.select(\"Option 1\");\n</code></pre>\n<p>To be continued...</p>","frontmatter":{"title":"Cypress Cheat Sheet."}}},"pageContext":{"slug":"/til0126/"}}